berhoel/ctitools/.__init__.py.~undo-tree~
berhoel/ctitools/.ct.py.~undo-tree~
berhoel/ctitools/.ix.py.~undo-tree~
berhoel/ctitools/__init__.py
"berhoel/ctitools/__init__.py,cover"
berhoel/ctitools/__main__.py
"berhoel/ctitools/__main__.py,cover"
berhoel/ctitools/ct.py
"berhoel/ctitools/ct.py,cover"
berhoel/ctitools/cti2bibtex/.__init__.py.~undo-tree~
berhoel/ctitools/cti2bibtex/__init__.py
"berhoel/ctitools/cti2bibtex/__init__.py,cover"
berhoel/ctitools/cti2bibtex/__main__.py
"berhoel/ctitools/cti2bibtex/__main__.py,cover"
berhoel/ctitools/cti2bibtex/tests/.test_generate.py.~undo-tree~
berhoel/ctitools/cti2bibtex/tests/__init__.py
berhoel/ctitools/cti2bibtex/tests/test_base.py
berhoel/ctitools/cti2bibtex/tests/test_generate.py
berhoel/ctitools/ctientry.py
"berhoel/ctitools/ctientry.py,cover"
berhoel/ctitools/ix.py
"berhoel/ctitools/ix.py,cover"
berhoel/ctitools/py.typed
berhoel/ctitools/tests/.ruff.toml
berhoel/ctitools/tests/.ruff_cache/.gitignore
berhoel/ctitools/tests/.ruff_cache/0.13.1/14727905688030155599
berhoel/ctitools/tests/.ruff_cache/0.13.1/1877863491161773674
berhoel/ctitools/tests/.ruff_cache/0.13.1/6802197673551834381
berhoel/ctitools/tests/.ruff_cache/0.14.0/3054254516174373000
berhoel/ctitools/tests/.ruff_cache/0.14.0/6498976333583442915
berhoel/ctitools/tests/.ruff_cache/0.5.7/16832089934128865244
berhoel/ctitools/tests/.ruff_cache/0.5.7/9544998460354806880
berhoel/ctitools/tests/.ruff_cache/0.6.4/12613539952892126951
berhoel/ctitools/tests/.ruff_cache/0.6.4/16163046912497964359
berhoel/ctitools/tests/.ruff_cache/0.8.0/10222943714603277521
berhoel/ctitools/tests/.ruff_cache/0.8.0/13699033895614806073
berhoel/ctitools/tests/.ruff_cache/0.8.4/11857819078074843794
berhoel/ctitools/tests/.ruff_cache/0.9.4/3108343357548289732
berhoel/ctitools/tests/.ruff_cache/0.9.4/6604047908265001070
berhoel/ctitools/tests/.ruff_cache/0.9.6/12779248252542523469
berhoel/ctitools/tests/.ruff_cache/0.9.6/7841673649433979510
ctitools-0.6.3.dist-info/WHEEL
ctitools-0.6.3.dist-info/entry_points.txt
ctitools-0.6.3.dist-info/METADATA
ctitools-0.6.3.dist-info/RECORD
