Metadata-Version: 2.3
Name: ctitools
Version: 0.6.3
Summary: Work with cti index files for the Heise papers c't and iX
Author: Berthold Höllmann
Author-email: Berthold Höllmann <berthold-gitlab@xn--hllmanns-n4a.de>
License: BSD 3
Classifier: Development Status :: 1 - Planning
Classifier: Environment :: Console
Classifier: Intended Audience :: End Users/Desktop
Classifier: License :: OSI Approved :: BSD License
Classifier: Natural Language :: German
Classifier: Programming Language :: Python :: 3
Classifier: Topic :: Utilities
Requires-Dist: click
Requires-Dist: rich
Requires-Dist: typing-extensions
Maintainer: Berthold Höllmann
Maintainer-email: Berthold Höllmann <berthold-gitlab@xn--hllmanns-n4a.de>
Requires-Python: >=3.13, <4.0
Project-URL: Documentation, https://python.xn--hllmanns-n4a.de/ctitools/
Project-URL: Homepage, https://python.xn--hllmanns-n4a.de/
Project-URL: Repository, https://gitlab.com/berhoel/python/ctitools.git
